tinx/__init__.py
tinx/utils.py
TINX-0.0.1.dist-info/LICENSE
TINX-0.0.1.dist-info/METADATA
TINX-0.0.1.dist-info/WHEEL
TINX-0.0.1.dist-info/top_level.txt
TINX-0.0.1.dist-info/RECORD
